gitfive/__init__.py
gitfive/config.py
gitfive/gitfive.py
gitfive/lib/__init__.py
gitfive/lib/api.py
gitfive/lib/banner.py
gitfive/lib/cli.py
gitfive/lib/close_friends.py
gitfive/lib/commits.py
gitfive/lib/domain_finder.py
gitfive/lib/emails_gen.py
gitfive/lib/github.py
gitfive/lib/instruments.py
gitfive/lib/metamon.py
gitfive/lib/objects.py
gitfive/lib/organizations.py
gitfive/lib/pea.py
gitfive/lib/repos.py
gitfive/lib/social.py
gitfive/lib/utils.py
gitfive/lib/xray.py
gitfive/modules/__init__.py
gitfive/modules/email_mod.py
gitfive/modules/emails_mod.py
gitfive/modules/light_mod.py
gitfive/modules/login_mod.py
gitfive/modules/username_mod.py
gitfive/version.py
gitfive-1.1.9.dist-info/LICENSE.md
gitfive-1.1.9.dist-info/METADATA
gitfive-1.1.9.dist-info/WHEEL
gitfive-1.1.9.dist-info/RECORD
