Metadata-Version: 2.1
Name: gitfive
Version: 1.1.9
Summary: Track down GitHub users.
License: MPL-2.0
Author: mxrch
Author-email: mxrch.dev@pm.me
Requires-Python: >=3.11,<4.0
Classifier: License :: OSI Approved
Classifier: Programming Language :: Python :: 3
Classifier: Programming Language :: Python :: 3.11
Classifier: Programming Language :: Python :: 3.12
Requires-Dist: alive-progress (>=3.1.5,<4.0.0)
Requires-Dist: anyio (>=4.6.0,<5.0.0)
Requires-Dist: beautifulsoup4 (>=4.12.3,<5.0.0)
Requires-Dist: gitpython (>=3.1.43,<4.0.0)
Requires-Dist: googlesearch-python (>=1.2.5,<2.0.0)
Requires-Dist: httpx (>=0.27.2,<0.28.0)
Requires-Dist: imagehash (>=4.3.1,<5.0.0)
Requires-Dist: levenshtein (>=0.26.0,<0.27.0)
Requires-Dist: packaging (>=24.1,<25.0)
Requires-Dist: pillow (>=10.4.0,<11.0.0)
Requires-Dist: pwinput (>=1.0.3,<2.0.0)
Requires-Dist: python-dateutil (>=2.9.0.post0,<3.0.0)
Requires-Dist: rich (>=13.9.1,<14.0.0)
Requires-Dist: trio (>=0.26.2,<0.27.0)
Requires-Dist: unidecode (>=1.3.8,<2.0.0)
